{
  "summary": "The video captures a snowy road with multiple vehicles traveling in both directions. A person walks along the sidewalk on the left side of the road.",
  "q_day_night": "Day",
  "q_weather": "Snowy",
  "q_ego_involved": "No",
  "actors_list": [
    {
      "id": "road_user_1",
      "type": "pedestrian"
    },
    {
      "id": "car_1",
      "type": "car"
    },
    {
      "id": "car_2",
      "type": "car"
    },
    {
      "id": "car_3",
      "type": "car"
    }
  ],
  "events_timeline": [
    {
      "t_start": 0.0,
      "t_end": 4.9,
      "event": "Multiple cars are seen driving on the road, including a white car moving ahead of the ego-vehicle.",
      "confidence": 0.95,
      "frame_indices": [
        0,
        4,
        7,
        14,
        21,
        28,
        35,
        42,
        49
      ]
    }
  ],
  "uncertainties": [
    "The identity of the pedestrians walking alongside the road is unclear.",
    "Some snow accumulation on the road may affect visibility."
  ],
  "risk_assessment": {
    "level": "Low",
    "why": "The primary concern is the snowy road conditions which could lead to reduced traction.",
    "confidence": 0.9
  },
  "metadata": {
    "model": "nvidia/Cosmos-Reason2-2B",
    "video_id": "000064",
    "frame_sampling": {
      "strategy": "uniform",
      "count": 8,
      "fps": 10.0
    },
    "generated_at": "2026-03-05T01:47:41.346744+00:00"
  }
}