{
  "summary": "Multiple vehicles are stopped at an intersection with traffic lights, including cars and trucks. Vehicles are halted in their respective lanes, and there is no apparent collision or disruption in the flow of traffic.",
  "q_day_night": "Day",
  "q_weather": "Normal",
  "q_ego_involved": "No",
  "actors_list": [
    {
      "id": "car_1",
      "type": "car"
    },
    {
      "id": "car_2",
      "type": "car"
    },
    {
      "id": "car_3",
      "type": "car"
    },
    {
      "id": "truck_1",
      "type": "truck"
    },
    {
      "id": "truck_2",
      "type": "truck"
    },
    {
      "id": "van_1",
      "type": "van"
    },
    {
      "id": "van_2",
      "type": "van"
    },
    {
      "id": "van_3",
      "type": "van"
    }
  ],
  "events_timeline": [
    {
      "t_start": 0.0,
      "t_end": 4.9,
      "event": "Multiple vehicles are stopped at an intersection with traffic lights, including cars and trucks. Vehicles are halted in their respective lanes, and there is no apparent collision or disruption in the flow of traffic.",
      "confidence": 0.99,
      "frame_indices": [
        0,
        4
      ]
    }
  ],
  "uncertainties": [
    "The precise reason for the vehicles' stoppage is unclear."
  ],
  "risk_assessment": {
    "level": "Low",
    "why": "There are no collisions or disruptions in the flow of traffic.",
    "confidence": 0.99
  },
  "metadata": {
    "model": "nvidia/Cosmos-Reason2-2B",
    "video_id": "001074",
    "frame_sampling": {
      "strategy": "uniform",
      "count": 8,
      "fps": 10.0
    },
    "generated_at": "2026-03-04T20:27:15.398834+00:00"
  }
}