{
  "summary": "The footage captures a city street with multiple lanes and tall buildings lining both sides. Vehicles are present, including cars and trucks, traveling in various directions. The road appears clear with no immediate obstacles or disruptions.",
  "q_day_night": "Day",
  "q_weather": "Normal",
  "q_ego_involved": "No",
  "actors_list": [
    {
      "id": "car_1",
      "type": "car"
    },
    {
      "id": "car_2",
      "type": "car"
    },
    {
      "id": "car_3",
      "type": "car"
    },
    {
      "id": "truck_1",
      "type": "truck"
    },
    {
      "id": "truck_2",
      "type": "truck"
    }
  ],
  "events_timeline": [
    {
      "t_start": 0.0,
      "t_end": 4.9,
      "event": "Multiple vehicles are seen moving along the city street, including cars and trucks.",
      "confidence": 0.95,
      "frame_indices": [
        0,
        4,
        7,
        14,
        21,
        28,
        35,
        42,
        49
      ]
    }
  ],
  "uncertainties": [
    "Exact positions and velocities of all vehicles are unclear due to limited visibility.",
    "Some background elements like pedestrians are not clearly visible."
  ],
  "risk_assessment": {
    "level": "Low",
    "why": "There are no apparent collisions, accidents, or hazardous behaviors evident in the provided frames.",
    "confidence": 0.95
  },
  "metadata": {
    "model": "nvidia/Cosmos-Reason2-2B",
    "video_id": "001146",
    "frame_sampling": {
      "strategy": "uniform",
      "count": 8,
      "fps": 10.0
    },
    "generated_at": "2026-03-04T20:04:16.540857+00:00"
  }
}